mocap_maya_operations/__init__.py
mocap_maya_operations/axengine_1728044231_3236386592.py
mocap_maya_operations/maya_export/__init__.py
mocap_maya_operations/maya_export/create_hik.py
mocap_maya_operations/maya_export/retarget_controllers.py
mocap_maya_operations/operations/__init__.py
mocap_maya_operations/operations/opsMayaExport.py
mocap_maya_operations-2.1.2.dist-info/METADATA
mocap_maya_operations-2.1.2.dist-info/WHEEL
mocap_maya_operations-2.1.2.dist-info/RECORD
