Metadata-Version: 2.1
Name: mocap-maya-operations
Version: 2.1.2
Summary: 
Keywords: MotionOps,Moveai
Author: move.ai
Author-email: info@move.ai
Requires-Python: >=3.10,<4.0
Classifier: Programming Language :: Python :: 3
Classifier: Programming Language :: Python :: 3.10
Classifier: Programming Language :: Python :: 3.11
Classifier: Programming Language :: Python :: 3.12
Requires-Dist: mocap-base (>=2.0.1,<3.0.0)
Requires-Dist: mocap-maya (>=0.2.3,<0.3.0)
Requires-Dist: mocap_settings (>=1.6.9,<2.0.0)
